{
  "coord": {
    "lon": -1.7812,
    "lat": 51.558
  },
  "weather": [
    {
      "id": 800,
      "main": "Clear",
      "description": "clear sky",
      "icon": "01n"
    }
  ],
  "base": "stations",
  "main": {
    "temp": 7.01,
    "feels_like": 4.55,
    "temp_min": 5.82,
    "temp_max": 7.09,
    "pressure": 1024,
    "humidity": 86,
    "sea_level": 1024,
    "grnd_level": 1008
  },
  "visibility": 10000,
  "wind": {
    "speed": 3.6,
    "deg": 200
  },
  "clouds": {
    "all": 0
  },
  "dt": 1765663683,
  "sys": {
    "type": 2,
    "id": 266740,
    "country": "GB",
    "sunrise": 1765613102,
    "sunset": 1765641471
  },
  "timezone": 0,
  "id": 2636389,
  "name": "Swindon",
  "cod": 200,
  "_last_updated_utc": "2025-12-13T22:08:03.377Z"
}