{
  "coord": {
    "lon": -1.7812,
    "lat": 51.558
  },
  "weather": [
    {
      "id": 804,
      "main": "Clouds",
      "description": "overcast clouds",
      "icon": "04n"
    }
  ],
  "base": "stations",
  "main": {
    "temp": 8.16,
    "feels_like": 6.84,
    "temp_min": 6.38,
    "temp_max": 8.2,
    "pressure": 1018,
    "humidity": 84,
    "sea_level": 1018,
    "grnd_level": 1000
  },
  "visibility": 10000,
  "wind": {
    "speed": 2.24,
    "deg": 232,
    "gust": 4.92
  },
  "clouds": {
    "all": 99
  },
  "dt": 1772327061,
  "sys": {
    "type": 2,
    "id": 266740,
    "country": "GB",
    "sunrise": 1772347980,
    "sunset": 1772387182
  },
  "timezone": 0,
  "id": 2636389,
  "name": "Swindon",
  "cod": 200,
  "_last_updated_utc": "2026-03-01T01:05:45.980Z"
}