{
  "coord": {
    "lon": -1.7812,
    "lat": 51.558
  },
  "weather": [
    {
      "id": 803,
      "main": "Clouds",
      "description": "broken clouds",
      "icon": "04d"
    }
  ],
  "base": "stations",
  "main": {
    "temp": 15.86,
    "feels_like": 14.94,
    "temp_min": 15.79,
    "temp_max": 16.8,
    "pressure": 1018,
    "humidity": 55,
    "sea_level": 1018,
    "grnd_level": 1002
  },
  "visibility": 10000,
  "wind": {
    "speed": 4.12,
    "deg": 220
  },
  "clouds": {
    "all": 75
  },
  "dt": 1776352555,
  "sys": {
    "type": 1,
    "id": 1495,
    "country": "GB",
    "sunrise": 1776316158,
    "sunset": 1776366251
  },
  "timezone": 3600,
  "id": 2636389,
  "name": "Swindon",
  "cod": 200,
  "_last_updated_utc": "2026-04-16T15:15:55.902Z"
}