{
  "coord": {
    "lon": -1.7812,
    "lat": 51.558
  },
  "weather": [
    {
      "id": 804,
      "main": "Clouds",
      "description": "overcast clouds",
      "icon": "04n"
    }
  ],
  "base": "stations",
  "main": {
    "temp": 6.75,
    "feels_like": 5.35,
    "temp_min": 5.27,
    "temp_max": 7.09,
    "pressure": 999,
    "humidity": 97,
    "sea_level": 999,
    "grnd_level": 983
  },
  "visibility": 10000,
  "wind": {
    "speed": 2.06,
    "deg": 360
  },
  "clouds": {
    "all": 100
  },
  "dt": 1769983853,
  "sys": {
    "type": 2,
    "id": 266740,
    "country": "GB",
    "sunrise": 1769931955,
    "sunset": 1769964920
  },
  "timezone": 0,
  "id": 2636389,
  "name": "Swindon",
  "cod": 200,
  "_last_updated_utc": "2026-02-01T22:10:53.773Z"
}