{
  "coord": {
    "lon": -1.7812,
    "lat": 51.558
  },
  "weather": [
    {
      "id": 801,
      "main": "Clouds",
      "description": "few clouds",
      "icon": "02d"
    }
  ],
  "base": "stations",
  "main": {
    "temp": 12.79,
    "feels_like": 11.35,
    "temp_min": 12.79,
    "temp_max": 12.8,
    "pressure": 1002,
    "humidity": 47,
    "sea_level": 1002,
    "grnd_level": 985
  },
  "visibility": 10000,
  "wind": {
    "speed": 2.57,
    "deg": 350
  },
  "clouds": {
    "all": 20
  },
  "dt": 1778774458,
  "sys": {
    "type": 1,
    "id": 1495,
    "country": "GB",
    "sunrise": 1778732212,
    "sunset": 1778788213
  },
  "timezone": 3600,
  "id": 2636389,
  "name": "Swindon",
  "cod": 200,
  "_last_updated_utc": "2026-05-14T16:01:26.463Z"
}