{
  "coord": {
    "lon": -1.7812,
    "lat": 51.558
  },
  "weather": [
    {
      "id": 803,
      "main": "Clouds",
      "description": "broken clouds",
      "icon": "04d"
    }
  ],
  "base": "stations",
  "main": {
    "temp": 10.55,
    "feels_like": 9.38,
    "temp_min": 10.55,
    "temp_max": 10.55,
    "pressure": 1023,
    "humidity": 66,
    "sea_level": 1023,
    "grnd_level": 1007
  },
  "visibility": 10000,
  "wind": {
    "speed": 3.3,
    "deg": 59,
    "gust": 6.49
  },
  "clouds": {
    "all": 59
  },
  "dt": 1776710781,
  "sys": {
    "country": "GB",
    "sunrise": 1776661250,
    "sunset": 1776712254
  },
  "timezone": 3600,
  "id": 2636389,
  "name": "Swindon",
  "cod": 200,
  "_last_updated_utc": "2026-04-20T18:46:21.824Z"
}