{
  "coord": {
    "lon": -1.7812,
    "lat": 51.558
  },
  "weather": [
    {
      "id": 500,
      "main": "Rain",
      "description": "light rain",
      "icon": "10d"
    }
  ],
  "base": "stations",
  "main": {
    "temp": 3.19,
    "feels_like": 0.6,
    "temp_min": 1.93,
    "temp_max": 3.2,
    "pressure": 993,
    "humidity": 91,
    "sea_level": 993,
    "grnd_level": 977
  },
  "visibility": 579,
  "wind": {
    "speed": 2.68,
    "deg": 7,
    "gust": 5.36
  },
  "rain": {
    "1h": 0.12
  },
  "clouds": {
    "all": 100
  },
  "dt": 1767946478,
  "sys": {
    "type": 2,
    "id": 266740,
    "country": "GB",
    "sunrise": 1767946227,
    "sunset": 1767975448
  },
  "timezone": 0,
  "id": 2636389,
  "name": "Swindon",
  "cod": 200,
  "_last_updated_utc": "2026-01-09T08:15:11.648Z"
}